pypath_setup/__init__.py
pypath_setup/__main__.py
pypath_setup-0.1.4.dist-info/entry_points.txt
pypath_setup-0.1.4.dist-info/WHEEL
pypath_setup-0.1.4.dist-info/METADATA
pypath_setup-0.1.4.dist-info/RECORD
